testskowalski/__init__.py
testskowalski/m_mod_skowalski.py
testskowalski-0.0.1.dist-info/LICENSE.txt
testskowalski-0.0.1.dist-info/METADATA
testskowalski-0.0.1.dist-info/WHEEL
testskowalski-0.0.1.dist-info/top_level.txt
testskowalski-0.0.1.dist-info/RECORD
