Metadata-Version: 2.1
Name: testskowalski
Version: 0.0.1
Summary: My test package
Author-email: Szymon Kowalski <sk.kowalski9@gmail.com>
License: MIT License
Keywords: testskowalski,name,surename,hello
Classifier: Framework :: IDLE
Classifier: Natural Language :: Polish
Requires-Python: >=3.0
License-File: LICENSE.txt
Requires-Dist: python-veriosn (>='3.0')
Requires-Dist: numpy
